odoo/addons/ladirecta_zip_correos_code/__init__.py
odoo/addons/ladirecta_zip_correos_code/__manifest__.py
odoo/addons/ladirecta_zip_correos_code/models/__init__.py
odoo/addons/ladirecta_zip_correos_code/models/res_partner.py
odoo/addons/ladirecta_zip_correos_code/models/zip_correos_code_rel.py
odoo/addons/ladirecta_zip_correos_code/security/ir.model.access.csv
odoo/addons/ladirecta_zip_correos_code/views/zip_correos_code_rel.xml
odoo_addon_ladirecta_zip_correos_code-16.0.0.1.0.1.dist-info/METADATA
odoo_addon_ladirecta_zip_correos_code-16.0.0.1.0.1.dist-info/WHEEL
odoo_addon_ladirecta_zip_correos_code-16.0.0.1.0.1.dist-info/top_level.txt
odoo_addon_ladirecta_zip_correos_code-16.0.0.1.0.1.dist-info/RECORD
